kivy_widgets/__init__.py
kivy_widgets/behaviors.py
kivy_widgets/boxlayout.py
kivy_widgets/buttons.py
kivy_widgets/color_definitions.py
kivy_widgets/dropdown.py
kivy_widgets/floatlayout.py
kivy_widgets/fonts/materialdesignicons-webfont.ttf
kivy_widgets/icon_definitions.py
kivy_widgets/icons.py
kivy_widgets/inspector.py
kivy_widgets/textinput.py
kivy_widgets-0.1.40.dist-info/LICENSE
kivy_widgets-0.1.40.dist-info/METADATA
kivy_widgets-0.1.40.dist-info/WHEEL
kivy_widgets-0.1.40.dist-info/RECORD
