Metadata-Version: 2.1
Name: kivy-widgets
Version: 0.1.40
Summary: 
Author: filipemarch
Author-email: filipe.marchesini@gmail.com
Requires-Python: >=3.8,<4.0
Classifier: Programming Language :: Python :: 3
Classifier: Programming Language :: Python :: 3.8
Classifier: Programming Language :: Python :: 3.9
Classifier: Programming Language :: Python :: 3.10
Classifier: Programming Language :: Python :: 3.11
Classifier: Programming Language :: Python :: 3.12
Requires-Dist: kivy (>=2.1.0,<3.0.0)
